extendedMD/__init__.py
extendedMD/bs.py
extendedMD/dtwdist.py
extendedMD/emd.py
extendedMD/mdl.py
extendedMD/motifs.py
extendedMD/patterns.py
extendedMD/pca.py
extendedMD/pruning.py
extendedMD/sax.py
extendedMD/viz.py
extendedMD-1.dist-info/METADATA
extendedMD-1.dist-info/RECORD
extendedMD-1.dist-info/WHEEL
extendedMD-1.dist-info/top_level.txt
