Metadata-Version: 2.1
Name: extendedMD
Version: 1
Summary: A small example package
Home-page: https://github.com/misilva73/extendedMD
Author: Maria Ines Silva
Author-email: misilva73@gmail.com
License: UNKNOWN
Project-URL: Documentation, https://extendedmd.readthedocs.io
Project-URL: Source, https://github.com/misilva73/extendedMD
Platform: UNKNOWN
Classifier: Programming Language :: Python :: 3
Classifier: License :: OSI Approved :: MIT License
Classifier: Operating System :: OS Independent
Requires-Python: >=3
Requires-Dist: dtaidistance (==1.1.4)
Requires-Dist: matplotlib (>=3.0.2)
Requires-Dist: numpy (>=1.15)
Requires-Dist: pandas (>=0.23)
Requires-Dist: saxpy (==1.0.1.dev167)
Requires-Dist: scipy (>=1.2)
Requires-Dist: seaborn (>=0.9)
